playlyfe-0.4.0.dist-info/DESCRIPTION.rst
playlyfe-0.4.0.dist-info/metadata.json
playlyfe-0.4.0.dist-info/top_level.txt
playlyfe-0.4.0.dist-info/RECORD
playlyfe-0.4.0.dist-info/WHEEL
playlyfe-0.4.0.dist-info/METADATA
src/playlyfe.py
