Metadata-Version: 2.0
Name: playlyfe
Version: 0.4.0
Summary: This is the official OAuth 2.0 Python client SDK for the Playlyfe API
Home-page: https://github.com/playlyfe/playlyfe-python-sdk
Author: Peter John
Author-email: peter@playlyfe.com
License: UNKNOWN
Keywords: REST,Playlyfe API,Playlyfe SDK,Gamification
Platform: UNKNOWN
Classifier: Development Status :: 3 - Alpha
Classifier: Intended Audience :: Developers
Classifier: Programming Language :: Python :: 2.7
